setup.py
rjmetrics/__init__.py
rjmetrics/client.py
rjmetrics/version.py
rjmetrics.egg-info/PKG-INFO
rjmetrics.egg-info/SOURCES.txt
rjmetrics.egg-info/dependency_links.txt
rjmetrics.egg-info/requires.txt
rjmetrics.egg-info/top_level.txt
rjmetrics/test/__init__.py
rjmetrics/test/test_client.py